MANIFEST.in
README.md
requirements.txt
setup.py
mongokat/__init__.py
mongokat/collection.py
mongokat/document.py
mongokat/exceptions.py
mongokat/utils.py
mongokat/version.py
mongokat.egg-info/PKG-INFO
mongokat.egg-info/SOURCES.txt
mongokat.egg-info/dependency_links.txt
mongokat.egg-info/entry_points.txt
mongokat.egg-info/not-zip-safe
mongokat.egg-info/requires.txt
mongokat.egg-info/top_level.txt
mongokat/_bson/_cbsonmodule.c
mongokat/_bson/buffer.c
mongokat/_bson/encoding_helpers.c
mongokat/_bson/time64.c